smartbox/__init__.py
smartbox/cmd.py
smartbox/error.py
smartbox/models.py
smartbox/py.typed
smartbox/reseller.py
smartbox/session.py
smartbox/socket.py
smartbox/update_manager.py
smartbox-2.4.0.dist-info/METADATA
smartbox-2.4.0.dist-info/WHEEL
smartbox-2.4.0.dist-info/entry_points.txt
smartbox-2.4.0.dist-info/licenses/LICENSE
smartbox-2.4.0.dist-info/RECORD
