Metadata-Version: 2.4
Name: smartbox
Version: 2.4.0
Summary: Python API to control heating 'smart boxes'
Project-URL: Homepage, https://github.com/ajtudela/smartbox
Project-URL: Issues, https://github.com/ajtudela/smartbox/issues
Author-email: Alberto Tudela <ajtudela@gmail.com>, Delmael <delmael@outlook.com>, graham33 <graham@grahambennett.org>
License-Expression: MIT
License-File: LICENSE
Classifier: License :: OSI Approved :: MIT License
Classifier: Operating System :: OS Independent
Classifier: Programming Language :: Python :: 3
Requires-Python: >=3.13
Requires-Dist: aiohttp
Requires-Dist: asyncclick
Requires-Dist: jq
Requires-Dist: pydantic==2.12.2
Requires-Dist: python-socketio
Requires-Dist: requests
Requires-Dist: websocket-client
